{
  "id": "media_slice",
  "type": "SharedSlice",
  "name": "MediaSlice",
  "description": "MediaSlice",
  "variations": [
    {
      "id": "default",
      "name": "Default",
      "docURL": "...",
      "version": "initial",
      "description": "Default",
      "imageUrl": "",
      "primary": {
        "title": {
          "type": "Text",
          "config": {
            "label": "Title",
            "placeholder": ""
          }
        },
        "content": {
          "type": "Text",
          "config": {
            "label": "Content",
            "placeholder": ""
          }
        }
      },
      "items": {
        "thumbnail": {
          "type": "Image",
          "config": {
            "label": "Thumbnail",
            "constraint": {},
            "thumbnails": []
          }
        },
        "media": {
          "type": "Link",
          "config": {
            "label": "Media",
            "placeholder": "",
            "select": "media"
          }
        },
        "embed_id": {
          "type": "Text",
          "config": {
            "label": "Embed id",
            "placeholder": ""
          }
        },
        "embed_platform": {
          "type": "Select",
          "config": {
            "label": "Embed platform",
            "placeholder": "",
            "options": [
              "Youtube",
              "Vimeo"
            ]
          }
        }
      }
    },
    {
      "id": "fullwidth",
      "name": "Fullwidth",
      "docURL": "...",
      "version": "initial",
      "description": "Default",
      "imageUrl": "",
      "primary": {
        "title": {
          "type": "Text",
          "config": {
            "label": "Title",
            "placeholder": ""
          }
        },
        "content": {
          "type": "Text",
          "config": {
            "label": "Content",
            "placeholder": ""
          }
        }
      },
      "items": {
        "thumbnail": {
          "type": "Image",
          "config": {
            "label": "Thumbnail",
            "constraint": {},
            "thumbnails": []
          }
        },
        "media": {
          "type": "Link",
          "config": {
            "label": "Media",
            "placeholder": "",
            "select": "media"
          }
        }
      }
    }
  ]
}